himawaripy/__init__.py
himawaripy/__main__.py
himawaripy/utils.py
himawaripy-2.2.0.dist-info/AUTHORS
himawaripy-2.2.0.dist-info/LICENSE
himawaripy-2.2.0.dist-info/METADATA
himawaripy-2.2.0.dist-info/WHEEL
himawaripy-2.2.0.dist-info/entry_points.txt
himawaripy-2.2.0.dist-info/top_level.txt
himawaripy-2.2.0.dist-info/RECORD
