Metadata-Version: 2.1
Name: himawaripy
Version: 2.2.0
Summary: himawaripy is a Python 3 script that fetches near-realtime (10 minutes delayed) picture of Earth as its taken by Himawari 8 (ひまわり8号) and sets it as your desktop background.
Home-page: https://labs.boramalper.org/himawaripy
Author: Bora M. Alper
Author-email: bora@boramalper.org
License: MIT
Platform: UNKNOWN
Requires-Dist: appdirs
Requires-Dist: pillow
Requires-Dist: python-dateutil
